agent_browser/__init__.py
agent_browser/driver.py
agent_browser/interactive.py
agent_browser/main.py
agent_browser/mcp.py
agent_browser/utils.py
agent_browser/cinematic/__init__.py
agent_browser/cinematic/annotations.py
agent_browser/cinematic/camera.py
agent_browser/cinematic/polish.py
agent_browser/cinematic/postproduction.py
agent_browser/cinematic/recording.py
agent_browser/cinematic/scripts.py
agent_browser/cinematic/tts.py
ai_agent_browser-0.2.7.dist-info/licenses/LICENSE
ai_agent_browser-0.2.7.dist-info/METADATA
ai_agent_browser-0.2.7.dist-info/WHEEL
ai_agent_browser-0.2.7.dist-info/entry_points.txt
ai_agent_browser-0.2.7.dist-info/top_level.txt
ai_agent_browser-0.2.7.dist-info/RECORD
