Metadata-Version: 2.4
Name: ai-agent-browser
Version: 0.2.7
Summary: A robust browser automation tool for AI agents - control browsers via CLI or IPC
Author: Agent Browser Contributors
License: GPL-3.0-only
Project-URL: Homepage, https://github.com/abhinav-nigam/agent-browser
Project-URL: Documentation, https://github.com/abhinav-nigam/agent-browser#readme
Project-URL: Repository, https://github.com/abhinav-nigam/agent-browser
Project-URL: Issues, https://github.com/abhinav-nigam/agent-browser/issues
Keywords: browser,automation,playwright,testing,ai,agent,mcp,claude-code,autonomous-agents,aider,llm-agent,ai-agent,browser-automation-cli,gpt-control,file-ipc,web-scraping-cli,headless-browser,cli-automation,llm-tools,ui-testing,browser-testing,agentic-testing,playwright-cli
Classifier: Development Status :: 4 - Beta
Classifier: Environment :: Console
Classifier: License :: OSI Approved :: GNU General Public License v3 (GPLv3)
Classifier: Intended Audience :: Developers
Classifier: Operating System :: OS Independent
Classifier: Programming Language :: Python :: 3
Classifier: Programming Language :: Python :: 3.10
Classifier: Programming Language :: Python :: 3.11
Classifier: Programming Language :: Python :: 3.12
Classifier: Topic :: Software Development :: Testing
Classifier: Topic :: Internet :: WWW/HTTP :: Browsers
Requires-Python: >=3.10
License-File: LICENSE
Requires-Dist: playwright>=1.40.0
Requires-Dist: pillow>=10.0.0
Requires-Dist: mcp>=1.0.0
Requires-Dist: pydantic>=2.0.0
Requires-Dist: aiohttp>=3.9.0
Provides-Extra: dev
Requires-Dist: pytest>=7.0.0; extra == "dev"
Requires-Dist: pytest-cov>=4.0.0; extra == "dev"
Requires-Dist: pytest-asyncio; extra == "dev"
Provides-Extra: video
Requires-Dist: openai>=1.0.0; extra == "video"
Requires-Dist: elevenlabs>=1.0.0; extra == "video"
Requires-Dist: mutagen>=1.47.0; extra == "video"
Dynamic: license-file
